odoo8_addon_product_multi_image-8.0.2.0.1-py2.7-nspkg.pth
odoo8_addon_product_multi_image-8.0.2.0.1.dist-info/DESCRIPTION.rst
odoo8_addon_product_multi_image-8.0.2.0.1.dist-info/METADATA
odoo8_addon_product_multi_image-8.0.2.0.1.dist-info/RECORD
odoo8_addon_product_multi_image-8.0.2.0.1.dist-info/WHEEL
odoo8_addon_product_multi_image-8.0.2.0.1.dist-info/metadata.json
odoo8_addon_product_multi_image-8.0.2.0.1.dist-info/namespace_packages.txt
odoo8_addon_product_multi_image-8.0.2.0.1.dist-info/top_level.txt
odoo_addons/product_multi_image/README.rst
odoo_addons/product_multi_image/__init__.py
odoo_addons/product_multi_image/__openerp__.py
odoo_addons/product_multi_image/hooks.py
odoo_addons/product_multi_image/i18n/ar.po
odoo_addons/product_multi_image/i18n/bg.po
odoo_addons/product_multi_image/i18n/bs.po
odoo_addons/product_multi_image/i18n/ca.po
odoo_addons/product_multi_image/i18n/cs.po
odoo_addons/product_multi_image/i18n/da.po
odoo_addons/product_multi_image/i18n/de.po
odoo_addons/product_multi_image/i18n/el.po
odoo_addons/product_multi_image/i18n/es.po
odoo_addons/product_multi_image/i18n/es_AR.po
odoo_addons/product_multi_image/i18n/es_CR.po
odoo_addons/product_multi_image/i18n/es_EC.po
odoo_addons/product_multi_image/i18n/es_MX.po
odoo_addons/product_multi_image/i18n/es_VE.po
odoo_addons/product_multi_image/i18n/et.po
odoo_addons/product_multi_image/i18n/fi.po
odoo_addons/product_multi_image/i18n/fr.po
odoo_addons/product_multi_image/i18n/gl.po
odoo_addons/product_multi_image/i18n/hr.po
odoo_addons/product_multi_image/i18n/hu.po
odoo_addons/product_multi_image/i18n/it.po
odoo_addons/product_multi_image/i18n/ja.po
odoo_addons/product_multi_image/i18n/lt.po
odoo_addons/product_multi_image/i18n/mk.po
odoo_addons/product_multi_image/i18n/mn.po
odoo_addons/product_multi_image/i18n/nb.po
odoo_addons/product_multi_image/i18n/nl.po
odoo_addons/product_multi_image/i18n/pl.po
odoo_addons/product_multi_image/i18n/pt.po
odoo_addons/product_multi_image/i18n/pt_BR.po
odoo_addons/product_multi_image/i18n/ro.po
odoo_addons/product_multi_image/i18n/ru.po
odoo_addons/product_multi_image/i18n/sl.po
odoo_addons/product_multi_image/i18n/sr.po
odoo_addons/product_multi_image/i18n/sv.po
odoo_addons/product_multi_image/i18n/tr.po
odoo_addons/product_multi_image/i18n/zh_CN.po
odoo_addons/product_multi_image/images/db.png
odoo_addons/product_multi_image/images/file.png
